{"trial_id": "00", "hyperparameters": {"space": [{"class_name": "Int", "config": {"name": "units", "default": null, "conditions": [], "min_value": 32, "max_value": 512, "step": 32, "sampling": "linear"}}, {"class_name": "Int", "config": {"name": "layers", "default": null, "conditions": [], "min_value": 1, "max_value": 4, "step": 1, "sampling": "linear"}}, {"class_name": "Choice", "config": {"name": "learning_rate", "default": 0.01, "conditions": [], "values": [0.01, 0.001, 0.0001], "ordered": true}}], "values": {"units": 128, "layers": 1, "learning_rate": 0.001}}, "metrics": {"metrics": {"accuracy": {"direction": "max", "observations": [{"value": [0.6953800717989603], "step": 1}]}, "loss": {"direction": "min", "observations": [{"value": [0.5824217200279236], "step": 1}]}, "val_accuracy": {"direction": "max", "observations": [{"value": [0.6916850606600443], "step": 1}]}, "val_loss": {"direction": "min", "observations": [{"value": [0.645093560218811], "step": 1}]}}}, "score": 0.6916850606600443, "best_step": 1, "status": "COMPLETED", "message": null}